FLite/__init__.py
FLite/config.yaml
FLite/coordinator.py
FLite/remote_service.py
FLite/client/BaseClient.py
FLite/client/__init__.py
FLite/client/service.py
FLite/communication/__init__.py
FLite/communication/grpc/__init__.py
FLite/communication/grpc/grpc_wrapper.py
FLite/datasets/BaseDatasets.py
FLite/datasets/FederatedDataset.py
FLite/datasets/__init__.py
FLite/datasets/cifar10/__init__.py
FLite/datasets/cifar10/cifar10.py
FLite/datasets/cifar100/__init__.py
FLite/datasets/cifar100/cifar100.py
FLite/datasets/data_processor/__init__.py
FLite/datasets/data_processor/cifar10.py
FLite/datasets/data_processor/cifar100.py
FLite/datasets/data_processor/femnist.py
FLite/datasets/data_processor/shakespeare.py
FLite/datasets/femnist/__init__.py
FLite/datasets/femnist/femnist.py
FLite/datasets/femnist/preprocess/__init__.py
FLite/datasets/femnist/preprocess/data_to_json.py
FLite/datasets/femnist/preprocess/get_file_dirs.py
FLite/datasets/femnist/preprocess/get_hashes.py
FLite/datasets/femnist/preprocess/group_by_writer.py
FLite/datasets/femnist/preprocess/match_hashes.py
FLite/datasets/shakespeare/__init__.py
FLite/datasets/shakespeare/shakespeare.py
FLite/datasets/shakespeare/preprocess/__init__.py
FLite/datasets/shakespeare/preprocess/gen_all_data.py
FLite/datasets/shakespeare/preprocess/preprocess_shakespeare.py
FLite/datasets/shakespeare/preprocess/shake_utils.py
FLite/datasets/utils/__init__.py
FLite/datasets/utils/constants.py
FLite/datasets/utils/data_loader.py
FLite/datasets/utils/datasets_download.py
FLite/datasets/utils/datasets_remove_users.py
FLite/datasets/utils/image_datasets_preprocess.py
FLite/datasets/utils/language_utils.py
FLite/datasets/utils/sample_collect.py
FLite/datasets/utils/save_load_util.py
FLite/datasets/utils/split_data.py
FLite/datasets/utils/splitdata_simulation.py
FLite/distribution/__init__.py
FLite/distribution/distributed.py
FLite/distribution/slurm.py
FLite/encryptor/Blowfish.py
FLite/encryptor/DES.py
FLite/encryptor/Salsa20.py
FLite-1.0.1.dist-info/LICENSE
FLite-1.0.1.dist-info/METADATA
FLite-1.0.1.dist-info/WHEEL
FLite-1.0.1.dist-info/top_level.txt
FLite-1.0.1.dist-info/RECORD
