Metadata-Version: 2.1
Name: FLite
Version: 1.0.1
Summary: FLite is a federated learning framework for developers to quickly build federated learning applications.(Design and Implementation of a Topology Based Distributed Training Federated Learning Experimental Framework.)[Software Engineering, School of Computer Science and Technology, WUST, P. Qi(Sensorjang@wust.edu.cn)]
Home-page: https://github.com/Sensorjang/FLite
Download-URL: https://github.com/Sensorjang/FLite.git
Author: P.Qi(Sensorjang)
Author-email: Sensorjang@wust.edu.cn
License: MIT License
Keywords: federated learning,machine learning,distributed machine learning,FL framework,privacy preserving
Classifier: Development Status :: 3 - Alpha
Classifier: License :: OSI Approved :: Apache Software License
Classifier: Topic :: Software Development :: Build Tools
Classifier: Operating System :: OS Independent
Classifier: Programming Language :: Python :: 3
Classifier: Programming Language :: Python :: 3.6
Classifier: Programming Language :: Python :: 3.7
Classifier: Programming Language :: Python :: 3.8
Classifier: Programming Language :: Python :: 3.9
License-File: LICENSE
Requires-Dist: etcd3 (==0.12.0)
Requires-Dist: google-auth (==1.21.2)
Requires-Dist: grpcio
Requires-Dist: grpcio-tools
Requires-Dist: kubernetes (==11.0.0)
Requires-Dist: numpy
Requires-Dist: omegaconf (==2.0.0)
Requires-Dist: requests (==2.24.0)
Requires-Dist: tqdm
Requires-Dist: pycryptodome
Provides-Extra: all
Requires-Dist: etcd3 (==0.12.0) ; extra == 'all'
Requires-Dist: google-auth (==1.21.2) ; extra == 'all'
Requires-Dist: grpcio ; extra == 'all'
Requires-Dist: grpcio-tools ; extra == 'all'
Requires-Dist: kubernetes (==11.0.0) ; extra == 'all'
Requires-Dist: numpy ; extra == 'all'
Requires-Dist: omegaconf (==2.0.0) ; extra == 'all'
Requires-Dist: requests (==2.24.0) ; extra == 'all'
Requires-Dist: tqdm ; extra == 'all'
Requires-Dist: pycryptodome ; extra == 'all'
